forestHog/__init__.py
forestHog/forestHog.py
forestHog/gitForest.py
forestHog-1.3.6.dist-info/LICENSE
forestHog-1.3.6.dist-info/METADATA
forestHog-1.3.6.dist-info/WHEEL
forestHog-1.3.6.dist-info/entry_points.txt
forestHog-1.3.6.dist-info/top_level.txt
forestHog-1.3.6.dist-info/RECORD
