Metadata-Version: 2.1
Name: forestHog
Version: 1.3.6
Summary: Searches through git repositories for high entropy strings, digging deep into commit history.
Home-page: https://github.com/EbryxLabs/forestHog
Author: Rana Awais
Author-email: rana.awais@ebryx.com
License: GNU
Platform: UNKNOWN
Classifier: Programming Language :: Python :: 3
Classifier: License :: OSI Approved :: GNU General Public License v2 (GPLv2)
Classifier: Operating System :: OS Independent
Requires-Dist: GitPython (==2.1.1)
Requires-Dist: truffleHogRegexes (==0.0.7)
